greedy/__init__.py
greedy/composite.py
greedy/descent.py
greedy/sampler.py
dwave_greedy-0.3.0.dist-info/LICENSE
dwave_greedy-0.3.0.dist-info/METADATA
dwave_greedy-0.3.0.dist-info/WHEEL
dwave_greedy-0.3.0.dist-info/top_level.txt
dwave_greedy-0.3.0.dist-info/RECORD
