Metadata-Version: 2.1
Name: dwave-greedy
Version: 0.3.0
Summary: Ocean-compatible collection of greedy/brute-force solvers/samplers
Home-page: https://github.com/dwavesystems/dwave-greedy
Author: D-Wave Systems Inc.
Author-email: tools@dwavesys.com
License: Apache 2.0
Project-URL: Documentation, https://docs.ocean.dwavesys.com/en/stable/docs_greedy/sdk_index.html
Project-URL: Issue Tracker, https://github.com/dwavesystems/dwave-greedy/issues/
Project-URL: Source Code, https://github.com/dwavesystems/dwave-greedy/
Classifier: License :: OSI Approved :: Apache Software License
Classifier: Operating System :: OS Independent
Classifier: Development Status :: 4 - Beta
Classifier: Programming Language :: Python :: 3
Classifier: Programming Language :: Python :: 3 :: Only
Classifier: Programming Language :: Python :: 3.7
Classifier: Programming Language :: Python :: 3.8
Classifier: Programming Language :: Python :: 3.9
Classifier: Programming Language :: Python :: 3.10
Classifier: Programming Language :: Python :: 3.11
Classifier: Programming Language :: Python :: Implementation :: CPython
Requires-Python: >=3.7
License-File: LICENSE
